samus_logging/__init__.py
samus_logging/level_filter.py
samus_logging/samus_logging.py
samus_logging-0.1.98.dist-info/LICENSE
samus_logging-0.1.98.dist-info/METADATA
samus_logging-0.1.98.dist-info/WHEEL
samus_logging-0.1.98.dist-info/top_level.txt
samus_logging-0.1.98.dist-info/RECORD
